ElGamalEllipticCurves/ElGamalEncryption.py
ElGamalEllipticCurves/EllipticCurve.py
ElGamalEllipticCurves/__init__.py
ElGamalEllipticCurves/modNum.py
ElGamalEllipticCurves-0.1.11.dist-info/LICENSE
ElGamalEllipticCurves-0.1.11.dist-info/METADATA
ElGamalEllipticCurves-0.1.11.dist-info/WHEEL
ElGamalEllipticCurves-0.1.11.dist-info/top_level.txt
ElGamalEllipticCurves-0.1.11.dist-info/RECORD
